pyStrint/__init__.py
pyStrint/cell_selection.py
pyStrint/evaluation.py
pyStrint/optimizers.py
pyStrint/plotting.py
pyStrint/prep_smurf.py
pyStrint/preprocess.py
pyStrint/strint.py
pyStrint/utils.py
pyStrint/LR/human_LR_pairs.txt
pyStrint/LR/mouse_LR_pairs.txt
pyStrint/pipelines/cal_cor.py
pyStrint/pipelines/kegg.R
pyStrint/pipelines/run_gsea.R
pyStrint/pipelines/run_leiden.py
pyStrint/pipelines/run_spatalk_lr.R
pyStrint/pipelines/run_spot_cor.py
pyStrint/pipelines/sankey.R
pyStrint/pipelines/spatialDE.py
pyStrint/pipelines/vis_spatalk.R
pystrint-0.0.29.dist-info/licenses/LICENSE
pystrint-0.0.29.dist-info/METADATA
pystrint-0.0.29.dist-info/WHEEL
pystrint-0.0.29.dist-info/top_level.txt
pystrint-0.0.29.dist-info/RECORD
